{
  "data_root": "../data/sample/xperience-10m-sample",
  "video": "fisheye_cam0.mp4",
  "target": "action",
  "num_windows": 1093,
  "split_strategy": "chronological",
  "purge_overlap": true,
  "rgb_embedding": "handcrafted",
  "model": "classical",
  "classes": [
    "Pick up kettle",
    "Position kettle to pour",
    "Move kettle",
    "Hold coffee carafe",
    "Grasp coffee scoop",
    "Transfer coffee to dripper",
    "Hold gooseneck kettle",
    "Grasp gooseneck kettle",
    "Lift gooseneck kettle",
    "Move kettle away",
    "Place kettle on table",
    "Pick up white bottle",
    "Pour liquid from white bottle",
    "Close bottle cap",
    "Place item on table",
    "Wait/Prepare for pouring",
    "Pour coffee",
    "Pour milk into coffee"
  ],
  "experiments": {
    "rgb_only_majority": {
      "accuracy": 0.0,
      "macro_f1": 0.0,
      "weighted_f1": 0.0,
      "balanced_accuracy": 0.0,
      "num_eval": 273,
      "num_classes": 18,
      "ece": 0.19094248116016388,
      "experiment": "rgb_only_majority",
      "model": "majority",
      "split_strategy": "chronological",
      "feature_dim": 686,
      "num_windows": 1093,
      "num_train": 817,
      "num_test": 273,
      "purge_overlap": true,
      "seed": 7
    },
    "rgb_only": {
      "accuracy": 0.003663003663003663,
      "macro_f1": 0.0034782608695652175,
      "weighted_f1": 6.370441153049849e-05,
      "balanced_accuracy": 0.2,
      "num_eval": 273,
      "num_classes": 18,
      "ece": 0.8020466229854486,
      "experiment": "rgb_only",
      "model": "softmax",
      "split_strategy": "chronological",
      "feature_dim": 686,
      "num_windows": 1093,
      "num_train": 817,
      "num_test": 273,
      "purge_overlap": true,
      "seed": 7
    },
    "hand_joints_only_majority": {
      "accuracy": 0.0,
      "macro_f1": 0.0,
      "weighted_f1": 0.0,
      "balanced_accuracy": 0.0,
      "num_eval": 273,
      "num_classes": 18,
      "ece": 0.19094248116016388,
      "experiment": "hand_joints_only_majority",
      "model": "majority",
      "split_strategy": "chronological",
      "feature_dim": 882,
      "num_windows": 1093,
      "num_train": 817,
      "num_test": 273,
      "purge_overlap": true,
      "seed": 7
    },
    "hand_joints_only": {
      "accuracy": 0.003663003663003663,
      "macro_f1": 0.023529411764705882,
      "weighted_f1": 0.00043094160741219563,
      "balanced_accuracy": 0.2,
      "num_eval": 273,
      "num_classes": 18,
      "ece": 0.7332939067821362,
      "experiment": "hand_joints_only",
      "model": "softmax",
      "split_strategy": "chronological",
      "feature_dim": 882,
      "num_windows": 1093,
      "num_train": 817,
      "num_test": 273,
      "purge_overlap": true,
      "seed": 7
    },
    "rgb_hand_fusion_majority": {
      "accuracy": 0.0,
      "macro_f1": 0.0,
      "weighted_f1": 0.0,
      "balanced_accuracy": 0.0,
      "num_eval": 273,
      "num_classes": 18,
      "ece": 0.19094248116016388,
      "experiment": "rgb_hand_fusion_majority",
      "model": "majority",
      "split_strategy": "chronological",
      "feature_dim": 1568,
      "num_windows": 1093,
      "num_train": 817,
      "num_test": 273,
      "purge_overlap": true,
      "seed": 7
    },
    "rgb_hand_fusion": {
      "accuracy": 0.003663003663003663,
      "macro_f1": 0.0125,
      "weighted_f1": 0.00022893772893772894,
      "balanced_accuracy": 0.2,
      "num_eval": 273,
      "num_classes": 18,
      "ece": 0.7474918649310157,
      "experiment": "rgb_hand_fusion",
      "model": "softmax",
      "split_strategy": "chronological",
      "feature_dim": 1568,
      "num_windows": 1093,
      "num_train": 817,
      "num_test": 273,
      "purge_overlap": true,
      "seed": 7
    },
    "rgb_hand_late_fusion": {
      "accuracy": 0.003663003663003663,
      "macro_f1": 0.006349206349206349,
      "weighted_f1": 0.00011628583057154485,
      "balanced_accuracy": 0.2,
      "num_eval": 273,
      "num_classes": 18,
      "ece": 0.5160219090762155,
      "experiment": "rgb_hand_late_fusion",
      "model": "late_fusion_softmax",
      "split_strategy": "chronological",
      "num_test": 273,
      "purge_overlap": true,
      "seed": 7
    }
  }
}